asmint/__init__.py
asmint/__main__.py
asmint/interpreter.py
assembler_interpreter-0.1.1.dist-info/LICENSE
assembler_interpreter-0.1.1.dist-info/METADATA
assembler_interpreter-0.1.1.dist-info/WHEEL
assembler_interpreter-0.1.1.dist-info/entry_points.txt
assembler_interpreter-0.1.1.dist-info/top_level.txt
assembler_interpreter-0.1.1.dist-info/RECORD
