Metadata-Version: 2.1
Name: assembler-interpreter
Version: 0.1.1
Summary: Interprets programs in assembly language
Author: Vlad Gavrilov
License: MIT License        
Project-URL: Homepage, https://github.com/vlad-gavrilov/assembler-interpreter
Project-URL: Bug Tracker, https://github.com/vlad-gavrilov/assembler-interpreter/issues
Keywords: assembler,interpreter,cli
Classifier: License :: OSI Approved :: MIT License
Classifier: Programming Language :: Python
Classifier: Programming Language :: Python :: 3
Requires-Python: >=3.8
License-File: LICENSE
